CartiMorph_vxm/__init__.py
CartiMorph_vxm/generators.py
CartiMorph_vxm/py/__init__.py
CartiMorph_vxm/py/utils.py
CartiMorph_vxm/tf/__init__.py
CartiMorph_vxm/tf/layers.py
CartiMorph_vxm/tf/losses.py
CartiMorph_vxm/tf/networks.py
CartiMorph_vxm/tf/scripts/__init__.py
CartiMorph_vxm/tf/scripts/inference_img2temp_warpLabel.py
CartiMorph_vxm/tf/scripts/inference_temp2img_warpTempSeg.py
CartiMorph_vxm/tf/scripts/train_tempLearnModel.py
CartiMorph_vxm/tf/utils/__init__.py
CartiMorph_vxm/tf/utils/utils.py
CartiMorph_vxm-0.9.1.dist-info/LICENSE
CartiMorph_vxm-0.9.1.dist-info/METADATA
CartiMorph_vxm-0.9.1.dist-info/WHEEL
CartiMorph_vxm-0.9.1.dist-info/top_level.txt
CartiMorph_vxm-0.9.1.dist-info/RECORD
