Metadata-Version: 2.1
Name: CartiMorph-vxm
Version: 0.9.1
Summary: Image Registration with Convolutional Networks tailored for the CartiMorph framework
Home-page: https://github.com/YongchengYAO/CartiMorph-vxm
License: Apache 2.0
Keywords: deformation,registration,imaging,cnn,mri
Classifier: Intended Audience :: Science/Research
Classifier: Programming Language :: Python :: 3
Classifier: License :: OSI Approved :: Apache Software License
Classifier: Operating System :: OS Independent
Requires-Python: >=3.10
License-File: LICENSE
Requires-Dist: packaging
Requires-Dist: scikit-image
Requires-Dist: h5py
Requires-Dist: numpy
Requires-Dist: scipy
Requires-Dist: nibabel
Requires-Dist: neurite (>=0.2)
